huaweicloudsdkeip/__init__.py
huaweicloudsdkeip/v2/__init__.py
huaweicloudsdkeip/v2/eip_async_client.py
huaweicloudsdkeip/v2/eip_client.py
huaweicloudsdkeip/v2/model/__init__.py
huaweicloudsdkeip/v2/model/add_publicips_into_shared_bandwidth_option.py
huaweicloudsdkeip/v2/model/add_publicips_into_shared_bandwidth_request.py
huaweicloudsdkeip/v2/model/add_publicips_into_shared_bandwidth_request_body.py
huaweicloudsdkeip/v2/model/add_publicips_into_shared_bandwidth_response.py
huaweicloudsdkeip/v2/model/band_width_rules.py
huaweicloudsdkeip/v2/model/bandwidth_pkg_page.py
huaweicloudsdkeip/v2/model/bandwidth_pkg_resp.py
huaweicloudsdkeip/v2/model/bandwidth_resp.py
huaweicloudsdkeip/v2/model/bandwidth_resp_insert.py
huaweicloudsdkeip/v2/model/batch_bandwidth.py
huaweicloudsdkeip/v2/model/batch_bandwidth_resp.py
huaweicloudsdkeip/v2/model/batch_create_bandwidth_option.py
huaweicloudsdkeip/v2/model/batch_create_bandwidth_request_body.py
huaweicloudsdkeip/v2/model/batch_create_publicip_tags_request.py
huaweicloudsdkeip/v2/model/batch_create_publicip_tags_request_body.py
huaweicloudsdkeip/v2/model/batch_create_publicip_tags_response.py
huaweicloudsdkeip/v2/model/batch_create_publicips_request.py
huaweicloudsdkeip/v2/model/batch_create_publicips_response.py
huaweicloudsdkeip/v2/model/batch_create_publicips_v2_request_body.py
huaweicloudsdkeip/v2/model/batch_create_shared_bandwidths_request.py
huaweicloudsdkeip/v2/model/batch_create_shared_bandwidths_response.py
huaweicloudsdkeip/v2/model/batch_delete_public_ip_request.py
huaweicloudsdkeip/v2/model/batch_delete_public_ip_request_body.py
huaweicloudsdkeip/v2/model/batch_delete_public_ip_response.py
huaweicloudsdkeip/v2/model/batch_delete_publicip_tags_request.py
huaweicloudsdkeip/v2/model/batch_delete_publicip_tags_request_body.py
huaweicloudsdkeip/v2/model/batch_delete_publicip_tags_response.py
huaweicloudsdkeip/v2/model/batch_disassociate_publicips_request.py
huaweicloudsdkeip-3.1.184.dist-info/METADATA
huaweicloudsdkeip-3.1.184.dist-info/WHEEL
huaweicloudsdkeip-3.1.184.dist-info/licenses/LICENSE
huaweicloudsdkeip-3.1.184.dist-info/RECORD
